g2o/__init__.py
g2o/g2opy.cp39-win_amd64.pyd
g2o_python-0.0.12.data/data/include/g2o/config.h
g2o_python-0.0.12.data/data/include/g2o/autodiff/LICENSE
g2o_python-0.0.12.data/data/include/g2o/autodiff/array_selector.h
g2o_python-0.0.12.data/data/include/g2o/autodiff/autodiff.h
g2o_python-0.0.12.data/data/include/g2o/autodiff/disable_warnings.h
g2o_python-0.0.12.data/data/include/g2o/autodiff/eigen.h
g2o_python-0.0.12.data/data/include/g2o/autodiff/fixed_array.h
g2o_python-0.0.12.data/data/include/g2o/autodiff/integer_sequence_algorithm.h
g2o_python-0.0.12.data/data/include/g2o/autodiff/jet.h
g2o_python-0.0.12.data/data/include/g2o/autodiff/memory.h
g2o_python-0.0.12.data/data/include/g2o/autodiff/parameter_dims.h
g2o_python-0.0.12.data/data/include/g2o/autodiff/reenable_warnings.h
g2o_python-0.0.12.data/data/include/g2o/autodiff/types.h
g2o_python-0.0.12.data/data/include/g2o/autodiff/variadic_evaluate.h
g2o_python-0.0.12.data/data/include/g2o/core/auto_differentiation.h
g2o_python-0.0.12.data/data/include/g2o/core/base_binary_edge.h
g2o_python-0.0.12.data/data/include/g2o/core/base_dynamic_vertex.h
g2o_python-0.0.12.data/data/include/g2o/core/base_edge.h
g2o_python-0.0.12.data/data/include/g2o/core/base_fixed_sized_edge.h
g2o_python-0.0.12.data/data/include/g2o/core/base_fixed_sized_edge.hpp
g2o_python-0.0.12.data/data/include/g2o/core/base_multi_edge.h
g2o_python-0.0.12.data/data/include/g2o/core/base_unary_edge.h
g2o_python-0.0.12.data/data/include/g2o/core/base_variable_sized_edge.h
g2o_python-0.0.12.data/data/include/g2o/core/base_variable_sized_edge.hpp
g2o_python-0.0.12.data/data/include/g2o/core/base_vertex.h
g2o_python-0.0.12.data/data/include/g2o/core/base_vertex.hpp
g2o_python-0.0.12.data/data/include/g2o/core/batch_stats.h
g2o_python-0.0.12.data/data/include/g2o/core/block_solver.h
g2o_python-0.0.12.data/data/include/g2o/core/block_solver.hpp
g2o_python-0.0.12.data/data/include/g2o/core/cache.h
g2o_python-0.0.12.data/data/include/g2o/core/creators.h
g2o_python-0.0.12.dist-info/LICENSE
g2o_python-0.0.12.dist-info/METADATA
g2o_python-0.0.12.dist-info/WHEEL
g2o_python-0.0.12.dist-info/top_level.txt
g2o_python-0.0.12.dist-info/RECORD
